pepver/__init__.py
pepver/py.typed
pepver-1.1.post1.dist-info/LICENSE
pepver-1.1.post1.dist-info/METADATA
pepver-1.1.post1.dist-info/WHEEL
pepver-1.1.post1.dist-info/RECORD
